Metadata-Version: 2.1
Name: tdk-search
Version: 1.0.1
Summary: fetches meanings of the turkish words from sozluk.gov.tr
Home-page: https://github.com/xis/tdk
Author: Enes Furkan Olcay
Author-email: sarhosgitar@gmail.com
License: MIT
Platform: UNKNOWN
Classifier: Programming Language :: Python :: 3
Classifier: License :: OSI Approved :: MIT License
Classifier: Operating System :: OS Independent
